TOPSIS_Ansh_101803295/__init__.py
TOPSIS_Ansh_101803295/__main__.py
TOPSIS_Ansh_101803295-1.0.1.dist-info/LICENSE.txt
TOPSIS_Ansh_101803295-1.0.1.dist-info/METADATA
TOPSIS_Ansh_101803295-1.0.1.dist-info/WHEEL
TOPSIS_Ansh_101803295-1.0.1.dist-info/top_level.txt
TOPSIS_Ansh_101803295-1.0.1.dist-info/RECORD
