Metadata-Version: 2.1
Name: TOPSIS-Ansh-101803295
Version: 1.0.1
Summary: The Technique for Order of Preference by Similarity to the Ideal Solution
Home-page: https://github.com/anshgarg7/TOPSIS-Ansh-101803295
Author: Ansh Garg
Author-email: anshgarg7@gmail.com
License: UNKNOWN
Platform: UNKNOWN
Classifier: Programming Language :: Python :: 3
Classifier: License :: OSI Approved :: MIT License
Classifier: Operating System :: OS Independent
Requires-Dist: pandas
Requires-Dist: numpy (==1.19.3)
